{
  "promotions": [
  	 {
      "promoThumbnail": "images/tab_deposit.jpg",
      "promoTitle": "DỰ ĐOÁN THẮNG TIỀN CÙNG ASIAN CUP 2019",
      "promoSubTitle": "",
      "promoContent": "<p><strong class='text-green'>DỰ ĐOÁN THẮNG TIỀN CÙNG ASIAN CUP 2019</strong></p><p class='description'>Chương trình khuyến mãi dành cho tất cả các thành viên tham gia chơi sử dụng tiền tệ VNĐ tại Bet98vn.</p><p class='description'>Cùng Nhà cái uy tín Bet98vn đồng hành với giải đấu ASIAN CUP 2019 bằng cách tham gia chương trình khuyến mãi cá cược dự đoán tỷ số chính xác của đội tuyển bóng đá yêu thích tại các trận đấu có trong giải.</p><p class='description'>Điều kiện rút tiền:</p><ul style='line-height: 1.5; font-size: 1.9rem;'><li>Tiền thưởng cần được trải qua 5 lần cược tại bất kì sản phẩm yêu thích.</li><li>Yêu cầu đặt cược: (tiền nạp + tiền thắng) x 5 lần.</li><li>Chương trình khuyến mãi này không được áp dụng chung với các chương trình khuyến mãi khác.</li></ul> <a href='#promo22' class='fancybox-promo promo-fncybox mb-15'>Xem chi tiết</a><div id='promo22' style='display: none'> <strong>ĐIỀU KHOẢN & ĐIỀU KIỆN：</strong><ul><li>Thành viên tham gia đặt cược tại các trận đấu của giải ASIAN CUP 2019. Phiếu cược hợp lệ có giá trị tối thiểu từ 500,000 VNĐ trở lên; đặt cược tỷ số chính xác (correct score); và phải được đặt cược trước giờ trận đấu diễn ra.</li><li>Thành viên sẽ nhận được tiền thưởng là 50,000 VNĐ x số bàn thắng của cả trận đấu.</li><li>Tiền thưởng tối đa mà mỗi thành viên có thể nhận mỗi trận đấu là 200,000 VNĐ.</li><li>Thành viên cần gửi yêu cầu tiền thưởng cho bộ phận hỗ trợ trực tuyến trong vòng 24 giờ kể từ khi trận đấu kết thúc để hợp lệ. Yêu cầu gửi quá thời hạn 24 giờ sẽ không được chấp nhận.</li><li>Tiền thưởng sẽ được cập nhật trong vòng 24 giờ kể từ lúc đăng kí nhận thưởng thành công với bộ phận hỗ trợ trực tuyến.</li><li><a href='termsCondition.html'>Điều Khoản Sử Dụng Khuyến Mãi</a> của Bet98vn được áp dụng.</li></ul></div>"
    },
     {	
      "promoThumbnail": "images/tab_deposit.jpg",
      "promoTitle": "DỰ ĐOÁN CẦU THỦ GIÀNH ĐƯỢC GIẢI CHIẾC GIÀY VÀNG CHÂU ÂU 2018 - 2019",
      "promoSubTitle": "",
      "promoContent": "<p><strong class='text-green'>DỰ ĐOÁN CẦU THỦ GIÀNH ĐƯỢC GIẢI “CHIẾC GIÀY VÀNG CHÂU ÂU 2018 - 2019”</strong></p><p class='description'>Chương trình khuyến mãi bắt đầu từ nay đến hết ngày 31/3/2019 (GMT+8) giành cho thành viên Bet98vn tham gia chơi với tiền tệ VNĐ.</p><p class='description'>Thành viên Bet98vn tham gia dự đoán cầu thủ giành được giải “Chiếc Giày Vàng Châu Âu 2018 - 2019” bằng cách:</p><p class='description'>Có số tiền gửi tối thiểu là 2,000,000 VNĐ và tham gia chơi tại Cá Cược Thể Thao trong thời gian diễn ra chương trình khuyến mãi.</p><p>Thành viên gửi email dự đoán cầu thủ được nhận giải theo mẫu sau :</p><ul style='line-height: 1.5; font-size: 1.9rem;'><li> Tiêu đề email : B98 – TÊN ĐĂNG NHẬP – DỰ ĐOÁN “CHIẾC GIÀY VÀNG CHÂU ÂU 2018 - 2019”</li><li>YTên đăng nhập tại Bet98vn : …………</li><li>Dự đoán cầu thủ đạt giải “Chiếc Giày Vàng Châu Âu 2018 - 2019”: …………</li><li>Tổng số bàn ghi được trong mùa giải: …………</li><li> Gửi email về địa chỉ : CS@bet98vn.com</li></ul> <a href='#promo22' class='fancybox-promo promo-fncybox mb-15'>Xem chi tiết</a><div id='promo22' style='display: none'> <strong>ĐIỀU KHOẢN & ĐIỀU KIỆN：</strong><ul><li>Thành viên đăng kí tham gia chương trình khuyến mãi bằng cách gửi email theo mẫu trên. Email phải được gửi trước khi chương trình khuyến mãi kết thúc vào ngày 31/3/2019 (GMT+8).</li><li>Thành viên trúng giải hợp lệ là thành viên có thỏa mãn 3 điều kiện sau :dự đoán chính xác cầu thủ đạt giải “Chiếc Giày Vàng Châu Âu 2018 - 2019”,dự đoán chính xác hoặc gần đúng nhất tổng số bàn thắng ghi được trong mùa giải,có tổng doanh thu cược tại Cá Cược Thể Thao cao nhất tính từ ngày 1/11/2018 đến hết ngày 31/3/2019 (GMT+8).</li><li>Các giải đấu hợp lệ được tính cho số bàn thắng của các cầu thủ là các trận đấu thuộc hệ thống các giải đấu hàng đầu quốc gia thuộc Liên đoàn bóng đá châu Âu.</li><li>Tiền thưởng và điểm thưởng sẽ được cập nhật trong vòng 24 giờ kể từ lúc ban tổ chức công bố kết quả cầu thủ nhận được giải “Chiếc Giày Vàng Châu Âu 2018 - 2019” và tổng số bàn thắng ghi được trong mùa giải.</li><li>Đối với thành viên may mắn trúng giải đặc biệt và áo thể thao, ban tổ chức sẽ liên hệ qua điện thoại để chúc mừng và cập nhật thông tin khách hàng để gửi quà.</li><li>Điều kiện rút tiền : Tiền thưởng phải được trải qua 10 lần cược tại bất kì sản phẩm yêu thích.</li><li><a href='termsCondition.html'>Điều Khoản Sử Dụng Khuyến Mãi</a> của Bet98vn được áp dụng.</li></ul></div>"
    },
    {
      "promoThumbnail": "images/tab_deposit.jpg",
      "promoTitle": "BET98VN - TẶNG 98,000 VNĐ TIỀN CƯỢC MIỄN PHÍ CHO THÀNH VIÊN MỚI",
      "promoSubTitle": "",
      "promoContent": "<p><strong class='text-green'>BET98VN – TẶNG 98,000 VNĐ TIỀN CƯỢC MIỄN PHÍ CHO THÀNH VIÊN MỚI</strong></p><p class='description'>Chương trình khuyến mãi bắt đầu từ nay đến hết ngày 31/12/2018 (GMT+8). Chương trình áp dụng cho thành viên mới đăng kí tài khoản trên Bet98vn.</p><p class='description'>Thành viên mới đăng kí sẽ được nhận 98,000 VNĐ tiền cược miễn phí để tham gia trải nghiệm tại nhà cái hàng đầu Châu Á (KHÔNG CẦN GỬI TIỀN)</p><p class='description'>Điều kiện rút tiền:</p><ul style='line-height: 1.5; font-size: 1.9rem;'><li>Thành viên nạp một số tiền bằng số tiền thắng (tiền nạp tối thiểu là 200,000 VNĐ).</li><li>Yêu cầu đặt cược: (tiền nạp + tiền thắng) x 5 lần.</li><li>Số tiền rút tối thiểu là 500,000 VNĐ.</li></ul> <a href='#promo22' class='fancybox-promo promo-fncybox mb-15'>Xem chi tiết</a><div id='promo22' style='display: none'> <strong>ĐIỀU KHOẢN & ĐIỀU KIỆN：</strong><ul><li>Khuyến mãi đến hết ngày 31/12/2018 (GMT+8).</li><li>Khuyến mãi chỉ áp dụng cho thành viên mới đăng kí tài khoản tại Bet98vn.</li><li>Tiền thưởng có giá trị trong vòng 7 ngày kể từ ngày phát hành.</li><li>Tiền thưởng sẽ bị hủy bỏ nếu thành viên chuyển tiền sang các trò chơi khác đặt cược khi chưa hoàn thành yêu cầu đặt cược.</li><li>Số tiền rút tối đa là 5,000,000 VNĐ.</li><li><a href='termsCondition.html'>Điều Khoản Sử Dụng Khuyến Mãi</a> của Bet98vn được áp dụng.</li></ul></div>"
    },
    {
      "promoThumbnail": "images/tab_deposit.jpg",
      "promoTitle": "BET98VN - KHUYẾN MÃI HOÀN TRẢ 2.5% CƯỢC XIÊN KHÔNG GIỚI HẠN TẠI CÁ CƯỢC THỂ THAO",
      "promoSubTitle": "",
      "promoContent": "<p><strong class='text-green'>BET98VN - KHUYẾN MÃI HOÀN TRẢ 2.5% CƯỢC XIÊN KHÔNG GIỚI HẠN TẠI CÁ CƯỢC THỂ THAO</strong></p> <ul> <li>Khuyến mãi dành cho Cá cược thể thao đến hết ngày 1/5/2018 (GMT+8).</li> <li>Tiền hoàn trả tối thiểu là 20,000 VND và không giới hạn tiền thưởng tối đa.</li> <li>Chỉ áp dụng cho các cược xiên thua 2 trận trở lên và tỷ lệ kèo là 1.5 trở lên.</li> </ul> <p><strong class='text-green'>Nhận thưởng Khuyến mãi hoàn trả với các gói thưởng như sau:</strong></p> <div class='table-responsive'> <table class='table table-bordered'> <thead> <tr> <th>Lựa chọn cược xiên</th> <th>Hoàn trả</th> </tr> </thead> <tbody> <tr> <td>Xiên 2</td> <td>2%</td> </tr> <tr> <td>Xiên 4</td> <td>2.1%</td> </tr> <tr> <td>Xiên 6</td> <td>2.2%</td> </tr> <tr> <td>Xiên 8 trở lên</td> <td>2.5%</td> </tr> </tbody> </table> </div> <a href='#promo1' class='fancybox-promo promo-fncybox mb-15'>Xem chi tiết</a> <div id='promo1' style='display: none'> <strong>ĐIỀU KHOẢN & ĐIỀU KIỆN：</strong> <ul> <li>Khuyến mãi này áp dụng cho các Thành viên Bet98vn sử dụng tiền tệ VNĐ.</li> <li>Thành viên sẽ liên hệ với hỗ trợ trực tuyến để nhận Hoàn trả không giới hạn dựa trên Vé Cược Xiên thua ở Cá cược thể thao, Bóng đá. Tiền thưởng sẽ được cập nhật trong vòng 24 giờ kể từ lúc có kết quả vé cược và được cập nhật vào ví chính.</li> <li>Yêu cầu đặt cược cho tiền thưởng 1 lần tại tỉ lệ kèo 1.50 trở lên.</li> <li>Cược vào tỷ lệ cược dưới 1.50 (MY: 0.5, HK: 0.5, Dec, Indo: 1.5), cược âm của tỷ lệ cược MY -0.5 trở xuống, cược hai bên, kết quả hòa, hoàn tiền, hủy hoặc vô hiệu và những cược đặt tại E-sports, Casino Trực Tuyến, Trò Chơi Slots sẽ không được tính là hợp lệ.</li> <li>Khuyến mãi này không được áp dụng chung với các khuyến mãi khác.</li><li><a href='termsCondition.html'>\"Điều Khoản Sử Dụng Khuyến Mãi\"</a> của Bet98vn được áp dụng.</li> </ul> </div>"
    },
    {
      "promoThumbnail": "images/tab_deposit.jpg",
      "promoTitle": "NHÀ CÁI BET98VN TẶNG TIỀN THƯỞNG SINH NHẬT LÊN ĐẾN 2.200.000VNĐ",
      "promoSubTitle": "",
      "promoContent": "<p><strong class='text-green'>Nhà cái Bet98vn tặng tiền thưởng sinh nhật lên đến 2.200.000vnđ</strong></p> <p class='description'> <b>Nhà cái Bet98vn</b> gửi lời chúc mừng sinh nhật đến các thành viên thân thiết với số tiền thưởng lên đến 2.200.000vnđ. Đây là một món quà nho nhỏ Bet98vn muốn tri ân và chia vui cùng thành viên trong ngày đặc biệt này. </p> <p><strong class='text-green'>Thể lệ nhận tiền thưởng sinh nhật tại Nhà cái Bet98vn:</strong></p> <p class='description'>Điều kiện để nhận thưởng vô cùng dễ dàng, thành viên chỉ cần có tổng số tiền nạp trong 3 tháng gần nhất là 3.000.000vnđ (khoản tiền này không áp dụng cho lần nạp nhận khuyến mãi nạp lần đầu). Thành viên sẽ nhận ngay 200.000vnđ tiền thưởng trong tháng sinh nhật.</p> <p class='description'>Ngoài ra, thành viên sẽ có cơ hội nhận thêm 30% tiền thưởng lên đến 2.000.000vnđ trong tháng sinh nhật.</p> <p class='description'><b>Nhà cái Bet98vn</b> xin chúc quý khách có một ngày sinh nhật thật nhiều niềm vui, may mắn và hạnh phúc bên cạnh gia đình và bạn bè. Đặc biệt là luôn luôn thắng lớn tại <b>Bet98vn</b>.</p> <p><strong class='text-green''>Liên hệ hỗ trợ trực tuyến để biết thêm chi tiết.</strong></p> <p><strong class='text-green'>Điều khoản và điều kiện:</strong></p> <p class='description'>Khuyến mãi sinh nhật này áp dụng cho tất cả các <b>thành viên tham gia tại Bet98vn</b>.</p> <p class='description'> Thành viên phải có tổng số tiền nạp trong 3 tháng gần nhất là 3.000.000vnđ (khoản tiền này không áp dụng cho lần nạp nhận khuyến mãi nạp lần đầu). <br /><br /> Điều kiện rút tiền: </p> <ul class='promo-ul' style='list-style:none'> <li>Đối với tiền thưởng 200.000vnđ. Thành viên phải đặt cược 3 lần cho <b>Cá Cược Thể Thao</b> hoặc 5 lần cho <b>Casino Trực tuyến</b> và <b> Trò chơi Slots</b>.</li> <li>Đối với tiền thưởng 2.000.000vnđ. Thành viên phải đặt cược 15 x ( Tiền nạp + tiền thưởng).</li> </ul> <br /> <p class='description'>Trong một số trường hợp cần thiết, Nhà cái Bet98vn có quyền yêu cầu thành viên cung cấp CMND để xét duyệt.</p> <a href='#promo2' class='fancybox-promo promo-fncybox mb-15'>Xem chi tiết</a><div id='promo2' style='display: none'><strong>ĐIỀU KHOẢN & ĐIỀU KIỆN：</strong> <ul class='list-style-decimal' style='margin-left:-15px;'><li><a href='termsCondition.html'>\"Điều Khoản Sử Dụng Khuyến Mãi\"</a> của Bet98vn được áp dụng.</li></ul></div>"
    },
    {
      "promoThumbnail": "images/tab_deposit.jpg",
      "promoTitle": "THƯỞNG 100% NẠP LẦN ĐẦU DÀNH CHO THỂ THAO",
      "promoSubTitle": "TIỀN THƯỞNG LÊN ĐẾN 1,500,000 VNĐ",
      "promoContent": "<p><strong class='text-green'>NHẬN TRỌN TIỀN THƯỞNG DỄ DÀNG SAU 3 BƯỚC:</strong></p> <ul class='list-style-decimal'> <li>Đăng ký tài khoản tại <a href='registration.html'>www.bet98vn.com</a></li> <li><p>Chọn một trong 3 loại khuyến mãi sau:</p><table> <thead> <tr> <th>Nạp tối thiểu</th> <th>Khuyến mãi</th> <th>Thưởng tối đa</th> <th>Số lần cược</th> </tr> </thead> <tbody> <tr> <td class='text-orange'>200,000 VNĐ</td> <td>100%</td> <td class='text-orange'>1,500,000 VNĐ</td> <td>22</td> </tr> <tr> <td class='text-orange'>200,000 VNĐ</td> <td>50%</td> <td class='text-orange'>3,000,000 VNĐ</td> <td>20</td> </tr> <tr> <td class='text-orange'>200,000 VNĐ</td> <td>30%</td> <td class='text-orange'>10,000,000 VNĐ</td> <td>15</td> </tr> </tbody> </table> </li> <li>Liên hệ Hỗ Trợ Trực Tuyến để nhận thưởng</li> </ul> <a href='#promo4' class='fancybox-promo promo-fncybox mb-15'>Xem chi tiết</a><div id='promo4' style='display: none'><strong>ĐIỀU KHOẢN & ĐIỀU KIỆN：</strong> <ul class='list-style-decimal' style='margin-left:-15px;'> <li>Khuyến mãi đến hết ngày 31/12/2018 (GMT+8).</li> <li>Khuyến mãi chỉ dành cho thành viên mới chưa nạp tiền ở Thể Thao tại nhà cái Bet98vn.</li> <li>Thành viên phải yêu cầu nhận thưởng sau khi nạp tiền thành công hoặc trước khi cược đầu tiên được đặt. Nếu không, tiền thưởng sẽ bị từ chối. Nếu thành viên đã thực hiện lệnh rút tiền thì thành viên sẽ không đủ điều kiện nhận khuyến mãi.</li> <li>Điều kiện rút tiền: (tiền nạp + tiền thưởng) x số lần cược tương ứng như bảng trên</li> <li>Cược vào tỷ lệ cược dưới 1.50 (MY: 0.5, HK: 0.5, Dec, Indo: 1.5), cược âm của tỷ lệ cược MY -0,5 trở xuống, cược hai bên, kết quả hòa, hoàn tiền, hủy hoặc vô hiệu và những cược đặt tại E-sports, Casino trực tuyến, Trò chơi Slots sẽ không tính vào doanh thu.</li> <li>Thành viên có thể nhận khuyến mãi Chào Mừng cho cả 3 sản phẩm Thể Thao, Casino Trực Tuyến và Trò Chơi Slots cùng một lúc nếu nạp tiền vào cả 3 sản phẩm. Khuyến mãi Chào Mừng không được áp dụng với các khuyến mãi khác.</li> <li>Thành viên không được quyền chuyển tiền sang Casino Trực Tuyến và Trò Chơi Slots để đặt cược. Nếu vi phạm, Bet98vn sẽ trừ hết tiền thưởng và tiền thắng trong tài khoản. Khoản tiền nạp ban đầu của thành viên vẫn sẽ được giữ lại trong tài khoản và cần đặt cược 1 lần để được phép rút tiền.</li> <li><a href='termsCondition.html'>\"Điều Khoản Sử Dụng Khuyến Mãi\"</a> của Bet98vn được áp dụng.</li></ul></div>"
    },
    {
      "promoThumbnail": "images/tab_deposit.jpg",
      "promoTitle": "THƯỞNG 100% NẠP LẦN ĐẦU DÀNH CHO TRÒ CHƠI SLOT",
      "promoSubTitle": "TIỀN THƯỞNG LÊN ĐẾN 1,500,000VND",
      "promoContent": "<p><strong class='text-green'>NHẬN TRỌN TIỀN THƯỞNG DỄ DÀNG SAU 3 BƯỚC:</strong></p> <ul class='list-style-decimal'> <li>Đăng ký tài khoản tại <a href='registration.html'>www.bet98vn.com</a></li> <li> <p>Bet98vn tặng khuyến mãi như sau:</p> <table> <thead> <tr> <th>Nạp tối thiểu</th> <th>Khuyến mãi</th> <th>Thưởng tối đa</th> <th>Số lần cược</th></tr> </thead> <tbody> <tr> <td class='text-orange'>200,000 VNĐ</td> <td>100%</td> <td class='text-orange'>1,500,000 VNĐ</td> <td>22</td> </tr> <tr> <td class='text-orange'>200,000 VNĐ</td> <td>50%</td> <td class='text-orange'>3,000,000 VNĐ</td> <td>20</td> </tr> <tr> <td class='text-orange'>200,000 VNĐ</td> <td>30%</td> <td class='text-orange'>10,000,000 VNĐ</td> <td>15</td> </tr> <tbody> </table> </li> <li>Liên hệ Hỗ Trợ Trực Tuyến để nhận khuyến mãi</li> </ul> <a href='#promo6' class='fancybox-promo promo-fncybox mb-15'>Xem chi tiết</a> <div id='promo6' style='display: none'> <strong>ĐIỀU KHOẢN & ĐIỀU KIỆN：</strong> <ul class='list-style-decimal' style='margin-left:-15px;'> <li>Khuyến mãi đến hết ngày 31/12/2018 (GMT+8).</li> <li>Khuyến mãi chỉ dành cho thành viên mới chưa nạp tiền ở Trò Chơi Slots tại nhà cái Bet98vn.</li> <li>Điều kiện rút tiền: (tiền nạp + tiền thưởng) x số lần cược tương ứng như bảng trên.</li> <li>Cược vào những trò chơi sau sẽ không được tính là hợp lệ: Tất cả Progresstive games, Spin a Win, tất cả các Blackjack, tất cả Roulette, tất cả Video Poker, tất cả Pontoon, tất cả Scratch games, tất cả Sic Bo, tất cả Craps, VIP Baccarat, Casino War, Casino Hold'em, Pai Gow Poker, tất cả multi-spin video slots và slots double up.</li> <li>Thành viên không được chuyển tiền sang các trò chơi khác đặt cược nếu chưa hoàn thành yêu cầu đặt cược, nếu không tất cả các tiền thắng cược và tiền thưởng sẽ bị hủy bỏ. Khoản tiền nạp ban đầu của thành viên sẽ vẫn được giữ lại trong tài khoản và cần đặt cược 1 lần để được phép rút tiền.</li> <li>Thành viên phải yêu cầu nhận thưởng sau khi nạp tiền thành công hoặc trước khi cược đầu tiên được đặt. Nếu không, tiền thưởng sẽ bị từ chối. Nếu thành viên đã thực hiện lệnh rút tiền thì thành viên sẽ không đủ điều kiện nhận khuyến mãi.</li> <li>Thành viên có thể nhận khuyến mãi Chào Mừng cho cả 3 sản phẩm Thể Thao, Casino Trực Tuyến và Trò Chơi Slots cùng một lúc nếu nạp tiền vào cả 3 sản phẩm. Khuyến mãi Chào Mừng không được áp dụng với các khuyến mãi khác.</li> <li><a href='termsCondition.html'>\"Điều Khoản Sử Dụng Khuyến Mãi\"</a> của Bet98vn được áp dụng.</li> </ul> </div>"
    },
    {
      "promoThumbnail": "images/tab_deposit.jpg",
      "promoTitle": "THƯỞNG 100% NẠP LẦN ĐẦU DÀNH CHO CASINO TRỰC TUYẾN",
      "promoSubTitle": "TIỀN THƯỞNG LÊN ĐẾN 2,000,000VND",
      "promoContent": "<p><strong class='text-green'>NHẬN TRỌN TIỀN THƯỞNG DỄ DÀNG SAU 3 BƯỚC:</strong></p> <ul class='list-style-decimal'> <li>Đăng ký tài khoản tại <a href='registration.html'>www.bet98vn.com</a></li> <li> <p>Bet98vn tặng khuyến mãi như sau:</p> <table> <thead> <tr> <th>Nạp tối thiểu</th> <th>Khuyến mãi</th> <th>Thưởng tối đa</th> <th>Số lần cược</th></tr> </thead> <tbody> <tr> <td class='text-orange'>200,000 VNĐ</td> <td>100%</td> <td class='text-orange'>2,000,000 VNĐ</td> <td>25</td> </tr> <tbody> </table> </li> <li>Liên hệ Hỗ Trợ Trực Tuyến để nhận khuyến mãi</li> </ul> <a href='#promo8' class='fancybox-promo promo-fncybox mb-15'>Xem chi tiết</a> <div id='promo8' style='display: none'> <strong>ĐIỀU KHOẢN & ĐIỀU KIỆN：</strong> <ul class='list-style-decimal' style='margin-left:-15px;'> <li>Khuyến mãi đến hết ngày 31/12/2018 (GMT+8).</li> <li>Khuyến mãi chỉ dành cho thành viên mới chưa nạp tiền ở Casino Trực Tuyến tại nhà cái Bet98vn.</li> <li>Thành viên phải gửi yêu cầu nhận thưởng sau khi nạp tiền thành công hoặc trước khi cược đầu tiên được đặt. Nếu không, tiền thưởng sẽ bị từ chối. Nếu thành viên đã thực hiện lệnh rút tiền thì thành viên sẽ không đủ điều kiện nhận khuyến mãi.</li> <li>Điều kiện rút tiền: (tiền nạp + tiền thưởng) x số lần cược tương ứng như bảng trên.</li> <li>Trong khuyến mãi Casino Trực Tuyến, cược vào Roulette sẽ không được tính vào yêu cầu đặt cược.</li> <li>Cược vào tất cả các trò chơi trong Trò chơi Slots sẽ không được tính là hợp lệ.</li> <li>Thành viên có thể nhận khuyến mãi Chào Mừng cho cả 3 sản phẩm Thể Thao, Casino Trực Tuyến và Trò Chơi Slots cùng một lúc nếu nạp tiền vào cả 3 sản phẩm. Khuyến mãi Chào Mừng không được áp dụng với các khuyến mãi khác.</li> <li>Thành viên không được quyền chuyển tiền sang các sản phẩm khác để đặt cược nếu chưa hoàn thành yêu cầu đặt cược. Nếu vi phạm, tất cả tiền thắng và tiền thưởng bị hủy bỏ. Khoản tiền nạp ban đầu của thành viên vẫn sẽ được giữ lại trong tài khoản và cần đặt cược 1 lần để được rút tiền.</li> <li><a href='termsCondition.html'>\"Điều Khoản Sử Dụng Khuyến Mãi\"</a> của Bet98vn được áp dụng.</li> </ul> </div>"
    },
    {
      "promoThumbnail": "images/tab_deposit.jpg",
      "promoTitle": "THƯỞNG THÀNH VIÊN TRUNG THÀNH",
      "promoSubTitle": "TIỀN THƯỞNG LÊN ĐẾN 1,000,000 VNĐ",
      "promoContent": "<p><strong class='text-green'>THƯỞNG THÀNH VIÊN TRUNG THÀNH</strong></p> <p>Chỉ cần tham gia với Bet98vn trong khoảng thời gian yêu cầu bên dưới, sẽ nhận ngay tiền thưởng:</p> <table> <thead> <tr> <th>Thời gian tham gia</th> <th>Tiền thưởng</th> <th>Yêu cầu đặt cược</th> </tr> </thead> <tbody> <tr> <td>3 tháng</td> <td class='text-orange'>300,000VND</td> <td>1x</td> </tr> <tr> <td>6 tháng</td> <td class='text-orange'>500,000VND</td> <td>1x</td> </tr> <tr> <td>9 tháng</td> <td class='text-orange'>700,000VND</td> <td>1x</td> </tr> <tr> <td>12 tháng</td> <td class='text-orange'>1,000,000VND</td> <td>1x</td> </tr> </tbody> </table> <p>Liên hệ Hỗ trợ trực tuyến để biết thêm chi tiết</p> <a href='#promo3' class='fancybox-promo promo-fncybox mb-15'>Xem chi tiết</a> <div id='promo3' style='display: none'> <strong>ĐIỀU KHOẢN & ĐIỀU KIỆN：</strong> <ul class='list-style-decimal' style='margin-left:-15px;'> <li>Cần 2 điều kiện để tính một tháng là hợp lệ:<br/> Tiền nạp – tiền rút = <span class='text-green'>3,000,000VND</span> và doanh thu cược là <span class='text-orange'>8,000,000VND</span></li> <li>Không được cược quá 50% số tiền thưởng trong một lần cược.</li> <li>Khuyến mãi có hiệu lực khi khách hàng thực hiện trong thời gian yêu cầu liên tục. Nếu có 1 tháng bị đứt quãng, những tháng trước sẽ không tính và sẽ tính lại từ đầu từ tháng sau.</li> <li><a href='termsCondition.html'>\"Điều Khoản Sử Dụng Khuyến Mãi\"</a> của Bet98vn được áp dụng.</li> </ul> </div>"
    },
    {
      "promoThumbnail": "images/tab_special.jpg",
      "promoTitle": "TẶNG 20% KHUYẾN MÃI CUỐI TUẦN",
      "promoSubTitle": "TIỀN THƯỞNG LÊN ĐẾN 2,000,000VND",
      "promoContent": "<p><strong class='text-green'>NHẬN 20% TIỀN THƯỞNG DỄ DÀNG MỖI CUỐI TUẦN VỚI CÁC BƯỚC SAU:</strong></p>  <ul class='list-style-decimal'> <li> <p>Nạp tiền vào tài khoản Bet98vn vào 2 ngày cuối tuần Thứ Bảy và Chủ Nhật. Chưa có tài khoản tại Bet98vn? <a href='registration.html'>Đăng ký ngay</a>.</p> <p class='text-orange'>Bet98vn tặng tiền thưởng cuối tuần như sau:</p> <table> <thead> <tr> <th></th> <th>Thưởng miễn phí</th> <th>Số lần cược</th> <th>Tiền thưởng tối đa</th> </tr> </thead> <tbody> <tr> <td>Thể thao</td> <td class='text-orange'>20%</td> <td class='text-orange'>15</td> <td class='text-orange'>2,000,000 VNĐ</td> </tr> <tr> <td>Casino trực tuyến</td> <td class='text-orange'>20%</td> <td class='text-orange'>15</td> <td class='text-orange'>2,000,000 VNĐ</td> </tr> <tr> <td>Trò chơi Slots</td> <td class='text-orange'>20%</td> <td class='text-orange'>15</td> <td class='text-orange'>2,000,000 VNĐ</td> </tr> </tbody> </table> </li> <li>Liên hệ Hỗ Trợ Trực Tuyến để nhận khuyến mãi.</li> </ul> <a href='#promo5' class='fancybox-promo promo-fncybox mb-15'>Xem chi tiết</a>  <div id='promo5' style='display: none'> <strong>ĐIỀU KHOẢN & ĐIỀU KIỆN：</strong> <ul class='list-style-decimal' style='margin-left:-15px;'> <li>Khuyến mãi đến hết ngày 31/12/2018 (GMT+8).</li> <li>Thành viên liên hệ Hỗ Trợ Trực Tuyến sau khi nạp tiền thành công hoặc trước khi cược đầu tiên được đặt. Nếu không, tiền thưởng sẽ bị từ chối. Nếu thành viên đã thực hiện lệnh rút tiền thì thành viên sẽ không đủ điều kiện nhận khuyến mãi.</li> <li> <p>Điều kiện rút tiền: (tiền nạp + tiền thưởng) x số lần cược theo bảng trên.</p> <ul class='list-style-decimal' style='margin-left:-15px;'> <li>Đối với Thể Thao: Cược vào tỷ lệ cược dưới 1.50 (MY: 0.5, HK: 0.5, Dec, Indo: 1.5), cược âm của tỷ lệ cược MY từ -0.5 trở xuống, cược hai bên, kết quả hòa, hoàn tiền, hủy hoặc vô hiệu và những cược đặt tại E-sports, Casino trực tuyến, trò chơi Slots sẽ không được tính vào doanh thu.</li> <li>Đối với khuyến mãi Trò Chơi Slots cược vào những trò chơi sau sẽ không được tính là hợp lệ: Tất cả Progresstive Games, Spin a Win, tất cả các Blackjack, tất cả Roulette, tất cả Video Poker, tất cả Pontoon, tất cả Scratch games, tất cả Sic Bo, tất cả Craps, VIP Baccarat, Casino War, Casino Hold'em, Pai Gow Poker, tất cả multi-spin video slots và slots double up.</li> <li>Đối với Casino Trực Tuyến: cược vào Roulette sẽ không được tính vào yêu cầu đặt cược.</li> </ul> </li> <li>Thành viên có thể nhận khuyến mãi Cuối Tuần tương ứng với 3 sản phẩm Thể Thao, Casino Trực Tuyến và Trò Chơi Slots cùng một lúc nếu nạp tiền vào cả 3 sản phẩm (mỗi sản phẩm chỉ nhận 1 lần duy nhất). Khuyến mãi Cuối Tuần không được áp dụng với các khuyến mãi khác.</li> <li>Thành viên không được chuyển tiền sang các trò chơi khác đặt cược nếu chưa hoàn thành yêu cầu đặt cược, nếu không tất cả tiền thắng cược và tiền thưởng (nếu có) sẽ bị hủy bỏ. Khoản tiền nạp ban đầu của thành viên vẫn sẽ được giữ lại trong tài khoản và cần đặt cược 1 lần để được phép rút tiền.</li> <li><a href='termsCondition.html'>\"Điều Khoản Sử Dụng Khuyến Mãi\"</a> của Bet98vn được áp dụng.</li> </ul> </div>"
    },
    {
      "promoThumbnail": "images/tab_special.jpg",
      "promoTitle": "HOÀN TRẢ 0.3% THỂ THAO",
      "promoSubTitle": "TIỀN THƯỞNG KHÔNG GIỚI HẠN MỖI TUẦN",
      "promoContent": "<p><strong class='text-green'>HOÀN TRẢ 0.3% THỂ THAO KHÔNG GIỚI HẠN MỖI TUẦN</strong></p> <p> <ul class='list-style-decimal' style='list-style-type: disc;'> <li>Khuyến mãi đến hết ngày 31/12/2018 (GMT+8).</li> <li>Tiền hoàn trả tối thiểu là <span class='text-orange'>20,000 VNĐ</span> và <span class='text-orange'>không giới hạn</span> tiền thưởng tối đa</li> <li>Điều kiện rút tiền: cần đạt doanh thu cược 1 lần.</li> <li>Tiền thưởng sẽ được tự động cập nhật vào thứ 3 hàng tuần..</li> </ul> </p> <p>Liên hệ <b>Hỗ Trợ Trực Tuyến</b> để biết thêm chi tiết</p> <a href='#promo9' class='fancybox-promo promo-fncybox mb-15'>Xem chi tiết</a> <div id='promo9' style='display: none'> <strong>ĐIỀU KHOẢN & ĐIỀU KIỆN：</strong> <ul class='list-style-decimal' style='margin-left:-15px;'> <li>Khuyến mãi này áp dụng cho các Thành viên Bet98vn sử dụng tiền tệ VNĐ.</li> <li>Thành viên sẽ nhận Hoàn trả không giới hạn dựa trên tổng số tiền cược của Thể Thao. Mỗi tuần được tính từ Thứ hai đến Chủ Nhật (GMT+8). Tiền thưởng hoàn trả sẽ được tặng vào Thứ Ba mỗi tuần và được cập nhật vào ví chính.</li> <li>Chỉ những cược đặt trong tuần mới được tính vào tổng số tiền cược yêu cầu. Tổng số tiền cược ở các tuần trước đó sẽ không được tính.</li> <li>Cược vào tỷ lệ cược dưới 1.50 (MY: 0.5, HK: 0.5, Dec, Indo: 1.5), cược âm của tỷ lệ cược MY -0.5 trở xuống, cược hai bên, kết quả hòa, hoàn tiền, hủy hoặc vô hiệu và những cược đặt tại E-sports, Casino Trực Tuyến, Trò Chơi Slots sẽ không được tính vào doanh thu.</li> <li>Tất cả tiền thưởng đến từ những khuyến mãi khác được nhận trong khoản thời gian này sẽ không được tính vào doanh thu cho tiền thưởng hoàn trả của người chơi.</li> <li>Khuyến mãi này không được áp dụng với các khuyến mãi khác.</li> <li><a href='termsCondition.html'>\"Điều Khoản Sử Dụng Khuyến Mãi\"</a> của Bet98vn được áp dụng.</li> </ul> </div>"
    },
    {
      "promoThumbnail": "images/tab_special.jpg",
      "promoTitle": "HOÀN TRẢ CASINO TRỰC TUYẾN LÊN ĐẾN 0.5%",
      "promoSubTitle": "TIỀN THƯỞNG KHÔNG GIỚI HẠN MỖI TUẦN",
      "promoContent": "<p><strong class='text-green'>HOÀN TRẢ CASINO TRỰC TUYẾN KHÔNG GIỚI HẠN LÊN ĐẾN 0.5% MỖI TUẦN</strong></p><p>Khuyến mãi đến hết ngày 31/12/2018 (GMT+8).</p> <p> <ul class='list-style-decimal' style='list-style-type: disc;'> <li>Tiền hoàn trả tối thiểu là 20,000 VNĐ và không giới hạn tiền thưởng tối đa</li> <li>Điều kiện rút tiền: cần đạt doanh thu cược 1 lần.</li> <li>Tiền thưởng sẽ được tự động cập nhật vào thứ 3 hàng tuần</li> </ul> </p> <p>Liên hệ Hỗ Trợ Trực Tuyến để biết thêm chi tiết</p> <a href='#promo10' class='fancybox-promo promo-fncybox mb-15'>Xem chi tiết</a> <div id='promo10' style='display: none'> <strong>ĐIỀU KHOẢN & ĐIỀU KIỆN：</strong> <ul class='list-style-decimal' style='margin-left:-15px;'> <li>Khuyến mãi này áp dụng cho các thành viên Bet98vn sử dụng tiền tệ VNĐ.</li> <li>Thành viên sẽ nhận Hoàn trả không giới hạn mỗi tuần dựa trên tổng số tiền cược của Casino trực tuyến. Mỗi tuần được tính từ Thứ hai đến Chủ nhật (GMT +8). Tiền thưởng hoàn trả sẽ được tặng vào Thứ Ba mỗi tuần và được cập nhật vào Ví chính.</li> <li>Chỉ những cược đặt trong tuần mới được tính vào tổng số tiền cược yêu cầu. Tổng số tiền cược ở các tuần trước đó sẽ không được tính.</li> <li>Đối với Khuyến mãi hoàn trả Casino trực tuyến, cược vào Trò chơi Slots và Roulette sẽ không được tính là hợp lệ.</li> <li>Tất cả tiền thưởng đến từ những khuyến mãi khác được nhận trong khoảng thời gian này sẽ không được tính cho tiền thưởng hoàn trả của người chơi.</li> <li>Thành viên chỉ có thể nhận mỗi loại tiền thưởng từng lần. Để nhận loại tiền thưởng khác, thành viên cần hoàn thành yêu cầu đặt cược cho loại tiền thưởng hiện có.</li> <li><a href='termsCondition.html'>\"Điều Khoản Sử Dụng Khuyến Mãi\"</a> của Bet98vn được áp dụng.</li> </ul> </div>"
    },
    {
      "promoThumbnail": "images/tab_special.jpg",
      "promoTitle": "HOÀN TRẢ SLOT GAME LÊN ĐẾN 0.5%",
      "promoSubTitle": "TIỀN THƯỞNG KHÔNG GIỚI HẠN MỖI TUẦN",
      "promoContent": "<p><strong class='text-green'>HOÀN TRẢ 0.5% TRÒ CHƠI SLOT KHÔNG GIỚI HẠN MỖI TUẦN</strong></p> <p>Khuyến mãi đến hết ngày 31/12/2018 (GMT+8).</p> <p> <ul class='list-style-decimal' style='list-style-type: disc;'> <li>Tiền hoàn trả tối thiểu là 20,000 VNĐ và không giới hạn tiền thưởng tối đa</li> <li>Điều kiện rút tiền: cần đạt doanh thu cược 1 lần.</li> <li>Tiền thưởng sẽ được tự động cập nhật vào thứ 3 hàng tuần</li> </ul> </p> <p>Liên hệ Hỗ Trợ Trực Tuyến để biết thêm chi tiết</p> <a href='#promo11' class='fancybox-promo promo-fncybox mb-15'>Xem chi tiết</a> <div id='promo11' style='display: none'> <strong>ĐIỀU KHOẢN & ĐIỀU KIỆN：</strong> <ul class='list-style-decimal' style='margin-left:-15px;'> <li>Khuyến mãi này áp dụng cho các thành viên Bet98vn sử dụng tiền tệ VNĐ.</li> <li>Thành viên sẽ nhận Hoàn trả không giới hạn mỗi tuần dựa trên tổng số tiền cược của Trò Chơi Slots. Mỗi tuần được tính từ Thứ hai đến Chủ nhật (GMT +8). Tiền thưởng hoàn trả sẽ được tặng vào Thứ Ba mỗi tuần và được cập nhật vào Ví chính.</li> <li>Chỉ những cược đặt trong tuần mới được tính vào tổng số tiền cược yêu cầu. Tổng số tiền cược ở các tuần trước đó sẽ không được tính.</li> <li>Đối với Khuyến mãi hoàn trả Trò Chơi Slots, cược vào tất cả các trò chơi sau sẽ không được tính là hợp lệ: Tất cả Progressive games, Spin a Win, tất cả các Blackjack, tất cả các Roulette, tất cả Video Poker, tất cả Pontoon, tất cả Scratch Games, tất cả Sic Bo, tất cả Craps, VIP Baccarrat, Casino War, Casino Hold'em, Pai Gow Poker, tất cả multi-spin video slots và slots double up.</li> <li>Tất cả tiền thưởng đến từ những khuyến mãi khác được nhận trong khoảng thời gian này sẽ không được tính cho tiền thưởng hoàn trả của người chơi.</li> <li>Thành viên chỉ có thể nhận mỗi loại tiền thưởng từng lần. Để nhận loại tiền thưởng khác, thành viên cần hoàn thành yêu cầu đặt cược cho loại tiền thưởng hiện có.</li> <li>Tiền thưởng phải được chia làm nhiều lần đặt cược với mức tiền thưởng nhỏ hơn 50% số tiền khuyến mãi nhận được. Nếu thành viên đặt cược với số tiền cược lớn hơn 50% số tiền khuyến mãi nhận được, cho mỗi lần cược thì tiền khuyến mãi và tiền thắng cược từ tiền khuyến mãi sẽ bị tịch thu.</li> <li><a href='termsCondition.html'>\"Điều Khoản Sử Dụng Khuyến Mãi\"</a> của Bet98vn được áp dụng.</li> </ul> </div>"
    }
  ]
}
